scaffold/__init__.py
scaffold/cli.py
scaffold/config.py
scaffold/core.py
scaffold/exceptions.py
scaffold/functions.py
scaffold/helpers.py
scaffold/models.py
scaffold/morphologies.py
scaffold/networks.py
scaffold/output.py
scaffold/particles.py
scaffold/plotting.py
scaffold/postprocessing.py
scaffold/reporting.py
scaffold/simulation.py
scaffold/statistics.py
scaffold/trees.py
scaffold/voxels.py
scaffold/configurations/casali_2019.json
scaffold/configurations/mouse_cerebellum.json
scaffold/configurations/neuron.json
scaffold/connectivity/__init__.py
scaffold/connectivity/general.py
scaffold/connectivity/strategy.py
scaffold/connectivity/connectome/__init__.py
scaffold/connectivity/connectome/aa_purkinje.py
scaffold/connectivity/connectome/bcsc_purkinje.py
scaffold/connectivity/connectome/gap_junctions.py
scaffold/connectivity/connectome/glomerulus_golgi.py
scaffold/connectivity/connectome/glomerulus_granule.py
scaffold/connectivity/connectome/golgi_glomerulus.py
scaffold/connectivity/connectome/golgi_granule.py
scaffold/connectivity/connectome/granule_golgi.py
scaffold/connectivity/connectome/io_molecular.py
scaffold/connectivity/connectome/io_purkinje.py
scaffold/connectivity/connectome/mossy_dcn.py
scaffold/connectivity/connectome/mossy_glomerulus.py
scaffold/connectivity/connectome/pf_interneuron.py
scaffold/connectivity/connectome/pf_purkinje.py
scaffold/connectivity/connectome/purkinje_dcn.py
scaffold/connectivity/connectome/satellite.py
scaffold/connectivity/detailed/__init__.py
scaffold/connectivity/detailed/shared.py
scaffold/connectivity/detailed/touch_detection.py
scaffold/connectivity/detailed/voxel_intersection.py
scaffold/placement/__init__.py
scaffold/placement/arrays.py
scaffold/placement/particle.py
scaffold/placement/randomwalk.py
scaffold/placement/satellite.py
scaffold/placement/strategy.py
scaffold/simulators/__init__.py
scaffold/simulators/nest.py
scaffold/simulators/keyboard/__init__.py
scaffold/simulators/neuron/__init__.py
dbbs_scaffold-3.2.9.dist-info/LICENSE
dbbs_scaffold-3.2.9.dist-info/METADATA
dbbs_scaffold-3.2.9.dist-info/WHEEL
dbbs_scaffold-3.2.9.dist-info/entry_points.txt
dbbs_scaffold-3.2.9.dist-info/top_level.txt
dbbs_scaffold-3.2.9.dist-info/RECORD
