Metadata-Version: 2.1
Name: dbbs-scaffold
Version: 3.2.9
Summary: A package for modelling morphologically detailed neuronal microcircuits.
Home-page: https://github.com/dbbs-lab/scaffold
Author: Robin De Schepper, Alice Geminiani, Alberto Antonietti, Stefano Casali, Claudia Casselato, Egidio D'Angelo
Author-email: robingilbert.deschepper@unipv.it
License: GPLv3
Project-URL: Bug Tracker, https://github.com/dbbs-lab/scaffold/issues/
Project-URL: Documentation, https://dbbs-docs.rf.gd/
Project-URL: Source Code, https://github.com/dbbs-lab/scaffold/
Platform: UNKNOWN
Classifier: Programming Language :: Python :: 3
Classifier: Operating System :: OS Independent
Requires-Dist: h5py (>=2.9.0)
Requires-Dist: numpy (>=1.16.4)
Requires-Dist: scipy (>=1.3.1)
Requires-Dist: scikit-learn (>=0.20.3)
Requires-Dist: plotly (>=4.1.0)
Requires-Dist: rtree (>=0.9.3)
Provides-Extra: neuron
Requires-Dist: nrn-patch (>=2.0.0) ; extra == 'neuron'
Requires-Dist: dbbs-models ; extra == 'neuron'
Provides-Extra: dev
Requires-Dist: sphinx ; extra == 'dev'
Requires-Dist: sphinx-rtd-theme (>=0.4.3) ; extra == 'dev'
Requires-Dist: pyarmor ; extra == 'dev'
Requires-Dist: pre-commit ; extra == 'dev'
Requires-Dist: black ; extra == 'dev'
